onysys_opensearch/__init__.py
onysys_opensearch/onysys_opensearch.py
onysys_opensearch-0.1.dist-info/LICENSE.txt
onysys_opensearch-0.1.dist-info/METADATA
onysys_opensearch-0.1.dist-info/WHEEL
onysys_opensearch-0.1.dist-info/top_level.txt
onysys_opensearch-0.1.dist-info/RECORD
